DIYables_MicroPython_LCD_I2C/DIYables_MicroPython_LCD_I2C.py
DIYables_MicroPython_LCD_I2C/__init__.py
DIYables_MicroPython_LCD_I2C-0.1.0.dist-info/LICENSE
DIYables_MicroPython_LCD_I2C-0.1.0.dist-info/METADATA
DIYables_MicroPython_LCD_I2C-0.1.0.dist-info/WHEEL
DIYables_MicroPython_LCD_I2C-0.1.0.dist-info/top_level.txt
DIYables_MicroPython_LCD_I2C-0.1.0.dist-info/RECORD
